arkeo/__init__.py
arkeo/config.py
arkeo/indexer.py
arkeo/legacy.py
arkeo/loader.py
arkeo/processor.py
arkeo/utils.py
config/__init__.py
config/path.py
utils/__init__.py
utils/access.py
utils/json.py
utils/search.py
utils/setup.py
utils/text.py
arkeo-0.1.0.dist-info/METADATA
arkeo-0.1.0.dist-info/WHEEL
arkeo-0.1.0.dist-info/top_level.txt
arkeo-0.1.0.dist-info/RECORD
