Metadata-Version: 2.1
Name: arkeo
Version: 0.1.0
Summary: markdown archiver betasaurus
Home-page: https://github.com/arkeosaurus/arkeo
Author: arkeosaurus
Author-email: sun.kwon09@myhunter.cuny.edu
License: UNKNOWN
Keywords: document processing,archiving,indexing,markdown,corpus
Platform: UNKNOWN
Classifier: Development Status :: 3 - Alpha
Classifier: Intended Audience :: Developers
Classifier: License :: OSI Approved :: MIT License
Classifier: Programming Language :: Python :: 3
Classifier: Programming Language :: Python :: 3.8
Classifier: Programming Language :: Python :: 3.9
Classifier: Programming Language :: Python :: 3.10
Classifier: Programming Language :: Python :: 3.11
Classifier: Topic :: Text Processing
Classifier: Topic :: Internet :: WWW/HTTP :: Indexing/Search
Requires-Python: >=3.8
Requires-Dist: beautifulsoup4
Requires-Dist: html2text
Requires-Dist: newspaper3k
Requires-Dist: requests
Requires-Dist: tqdm
